AUTHORS.rst
CHANGELOG.rst
LICENSE
MANIFEST.in
README.rst
setup.py
django_google_credentials.egg-info/PKG-INFO
django_google_credentials.egg-info/SOURCES.txt
django_google_credentials.egg-info/dependency_links.txt
django_google_credentials.egg-info/not-zip-safe
django_google_credentials.egg-info/requires.txt
django_google_credentials.egg-info/top_level.txt
google_credentials/__init__.py
google_credentials/models.py
google_credentials/urls.py
google_credentials/utils.py
google_credentials/views.py